todd/__init__.py
todd/py.typed
todd/bases/__init__.py
todd/bases/configs/__init__.py
todd/bases/configs/base.py
todd/bases/registries/__init__.py
todd/bases/registries/base.py
todd/bases/registries/build_pre_hooks.py
todd/colors/__init__.py
todd/colors/color.py
todd/colors/color_wheel.py
todd/colors/constants.py
todd/colors/palette.py
todd/colors/rgba.py
todd/colors/yiq.py
todd/configs/__init__.py
todd/configs/diff.py
todd/configs/py_.py
todd/configs/serialize.py
todd/datasets/__init__.py
todd/datasets/base.py
todd/datasets/coco.py
todd/datasets/constants.py
todd/datasets/imagenet.py
todd/datasets/index.py
todd/datasets/laion_aesthetics.py
todd/datasets/lvis.py
todd/datasets/objects365.py
todd/datasets/pil.py
todd/datasets/registries.py
todd/datasets/sa_med2d.py
todd/datasets/satin.py
todd/datasets/v3det.py
todd/datasets/access_layers/__init__.py
todd/datasets/access_layers/base.py
todd/datasets/access_layers/concat.py
todd/datasets/access_layers/cv2.py
todd/datasets/access_layers/folder.py
todd/datasets/access_layers/hf.py
todd/datasets/access_layers/npy.py
todd/datasets/access_layers/pil.py
todd/datasets/access_layers/pth.py
todd/datasets/access_layers/suffix.py
todd/loggers/__init__.py
todd/loggers/formatter.py
todd/loggers/logger_.py
todd/loggers/master_logger_.py
todd/loggers/control_sequences/__init__.py
todd/loggers/control_sequences/control_sequence.py
todd/loggers/control_sequences/sgr.py
todd/models/__init__.py
todd/models/frozens.py
todd/models/mean_std.py
todd/models/norms.py
todd/models/registries.py
todd/models/torchvision.py
todd/models/filters/__init__.py
todd/models/filters/base.py
todd/models/filters/named_member.py
todd/models/filters/named_module.py
todd/models/filters/named_parameter.py
todd/models/losses/__init__.py
todd/models/losses/base.py
todd/models/losses/functional.py
todd/models/losses/registries.py
todd/models/losses/schedulers.py
todd/models/modules/__init__.py
todd/models/modules/attentions.py
todd/models/modules/clip.py
todd_ai-0.6.0.dist-info/licenses/LICENSE
todd_ai-0.6.0.dist-info/METADATA
todd_ai-0.6.0.dist-info/WHEEL
todd_ai-0.6.0.dist-info/entry_points.txt
todd_ai-0.6.0.dist-info/top_level.txt
todd_ai-0.6.0.dist-info/RECORD
