Metadata-Version: 2.4
Name: todd_ai
Version: 0.6.0
Summary: Toolkit for Object Detection Distillation
Author-email: Luting Wang <wangluting@buaa.edu.cn>
License:                                  Apache License
Project-URL: Homepage, https://github.com/LutingWang/todd
Project-URL: Documentation, https://toddai.readthedocs.io/en/latest/
Classifier: Programming Language :: Python :: 3
Classifier: License :: OSI Approved :: Apache Software License
Classifier: Operating System :: OS Independent
Requires-Python: >=3.11
License-File: LICENSE
Requires-Dist: datasets
Requires-Dist: einops
Requires-Dist: ffmpeg-python
Requires-Dist: lmdb
Requires-Dist: numpy<2.0
Requires-Dist: opencv-python
Requires-Dist: pycocotools
Requires-Dist: pydub
Requires-Dist: python-pptx
Requires-Dist: tensorboard
Requires-Dist: timm
Requires-Dist: toml
Requires-Dist: typing_extensions
Requires-Dist: yapf
Provides-Extra: optional
Requires-Dist: accelerate; extra == "optional"
Requires-Dist: beautifulsoup4; extra == "optional"
Requires-Dist: bitsandbytes; extra == "optional"
Requires-Dist: diffusers; extra == "optional"
Requires-Dist: ebooklib; extra == "optional"
Requires-Dist: ftfy; extra == "optional"
Requires-Dist: jieba; extra == "optional"
Requires-Dist: h5py; extra == "optional"
Requires-Dist: nltk; extra == "optional"
Requires-Dist: openmim; extra == "optional"
Requires-Dist: pandas[all]; extra == "optional"
Requires-Dist: pypinyin; extra == "optional"
Requires-Dist: regex; extra == "optional"
Requires-Dist: sentencepiece; extra == "optional"
Requires-Dist: tqdm; extra == "optional"
Requires-Dist: transformers==4.49.0; extra == "optional"
Requires-Dist: WeTextProcessing; extra == "optional"
Provides-Extra: dev
Requires-Dist: ipdb; extra == "dev"
Requires-Dist: ipykernel; extra == "dev"
Requires-Dist: jupyter; extra == "dev"
Requires-Dist: torch-tb-profiler; extra == "dev"
Provides-Extra: lint
Requires-Dist: autoflake; extra == "lint"
Requires-Dist: bandit[toml]; extra == "lint"
Requires-Dist: codespell; extra == "lint"
Requires-Dist: commitizen; extra == "lint"
Requires-Dist: doc8; extra == "lint"
Requires-Dist: docformatter[tomli]; extra == "lint"
Requires-Dist: flake8; extra == "lint"
Requires-Dist: flake8-bugbear; extra == "lint"
Requires-Dist: flake8-commas; extra == "lint"
Requires-Dist: flake8-docstrings; extra == "lint"
Requires-Dist: mccabe; extra == "lint"
Requires-Dist: mypy; extra == "lint"
Requires-Dist: pandas-stubs; extra == "lint"
Requires-Dist: pep8-naming; extra == "lint"
Requires-Dist: pre-commit; extra == "lint"
Requires-Dist: pydocstyle; extra == "lint"
Requires-Dist: pylint; extra == "lint"
Requires-Dist: types-beautifulsoup4; extra == "lint"
Requires-Dist: types-Pillow; extra == "lint"
Requires-Dist: types-pycocotools; extra == "lint"
Requires-Dist: types-regex; extra == "lint"
Requires-Dist: types-requests; extra == "lint"
Requires-Dist: types-toml; extra == "lint"
Requires-Dist: types-tqdm; extra == "lint"
Provides-Extra: doc
Requires-Dist: python-docs-theme; extra == "doc"
Requires-Dist: sphinx; extra == "doc"
Requires-Dist: sphinx_rtd_theme; extra == "doc"
Provides-Extra: test
Requires-Dist: coverage; extra == "test"
Requires-Dist: pytest; extra == "test"
Dynamic: license-file
